regex_builder/__init__.py
regex_builder/abc.py
regex_builder/constants.py
regex_builder/errors.py
regex_builder/misc.py
regex_builder/quantifiers.py
regex_builder/regex.py
regex_builder/section.py
regex_builder-1.0.0.dist-info/LICENSE
regex_builder-1.0.0.dist-info/METADATA
regex_builder-1.0.0.dist-info/WHEEL
regex_builder-1.0.0.dist-info/top_level.txt
regex_builder-1.0.0.dist-info/RECORD
